[{"id": 655601, "title": "Penne with Sausage, Tomatoes and Potatoes", "image": "https://spoonacular.com/recipeImages/655601-312x231.jpg", "imageType": "jpg", "usedIngredientCount": 2, "missedIngredientCount": 3, "missedIngredients": [{"id": 1001, "amount": 0.5, "unit": "pound", "unitLong": "pounds", "unitShort": "lb", "aisle": "Milk, Eggs, Other Dairy", "name": "butter", "original": "1/2 pound butter", "originalName": "butter", "meta": [], "image": "https://spoonacular.com/cdn/ingredients_100x100/butter-sliced.jpg"}, {"id": 7036, "amount": 4.0, "unit": "", "unitLong": "", "unitShort": "", "aisle": "Meat", "name": "italian sausages", "original": "4 sweet Italian sausages cut in chunks", "originalName": "sweet Italian sausages cut in chunks", "meta": ["sweet", "italian", "cut in chunks"], "extendedName": "sweet italian sausages", "image": "https://spoonacular.com/cdn/ingredients_100x100/raw-pork-sausage.png"}, {"id": 11120420, "amount": 1.0, "unit": "pound", "unitLong": "pound", "unitShort": "lb", "aisle": "Pasta and Rice", "name": "penne pasta", "original": "1 pound penne pasta", "originalName": "penne pasta", "meta": [], "image": "https://spoonacular.com/cdn/ingredients_100x100/penne-pasta.jpg"}], "usedIngredients": [{"id": 10011693, "amount": 15.0, "unit": "ounce", "unitLong": "ounces", "unitShort": "oz", "aisle": "Canned and Jarred", "name": "canned tomatoes", "original": "1 can (15- ounce) whole tomatoes, drained, roughly chopped", "originalName": "can whole tomatoes, drained, roughly chopped", "meta": ["whole", "drained", "roughly chopped", "canned"], "extendedName": "whole canned tomatoes", "image": "https://spoonacular.com/cdn/ingredients_100x100/tomatoes-canned.png"}, {"id": 11352, "amount": 2.0, "unit": "small", "unitLong": "smalls", "unitShort": "small", "aisle": "Produce", "name": "potatoes", "original": "2 small potatoes, peeled and cut into medium size cubes", "originalName": "potatoes, peeled and cut into medium size cubes", "meta": ["peeled", "cut into medium size cubes"], "image": "https://spoonacular.com/cdn/ingredients_100x100/potatoes-yukon-gold.png"}], "unusedIngredients": [], "likes": 4}, {"id": 633224, "title": "Baby Brie-Topped Potato Slices", "image": "https://spoonacular.com/recipeImages/633224-312x231.jpg", "imageType": "jpg", "usedIngredientCount": 2, "missedIngredientCount": 3, "missedIngredients": [{"id": 1006, "amount": 8.0, "unit": "oz", "unitLong": "ounces", "unitShort": "oz", "aisle": "Cheese", "name": "brie cheese", "original": "1 package (8 oz.) Alouette Baby Brie Cheese, cut into 24 wedges", "originalName": "package Alouette Baby Brie Cheese, cut into 24 wedges", "meta": ["cut into 24 wedges"], "image": "https://spoonacular.com/cdn/ingredients_100x100/brie.jpg"}, {"id": 2063, "amount": 2.0, "unit": "teaspoons", "unitLong": "teaspoons", "unitShort": "tsp", "aisle": "Produce", "name": "fresh rosemary leaves", "original": "2 teaspoons chopped fresh rosemary leaves", "originalName": "chopped fresh rosemary leaves", "meta": ["fresh", "chopped"], "image": "https://spoonacular.com/cdn/ingredients_100x100/rosemary.jpg"}, {"id": 1033, "amount": 1.0, "unit": "tablespoon", "unitLong": "tablespoon", "unitShort": "Tbsp", "aisle": "Cheese", "name": "parmesan cheese", "original": "1 tablespoon grated parmesan cheese", "originalName": "grated parmesan cheese", "meta": ["grated"], "image": "https://spoonacular.com/cdn/ingredients_100x100/parmesan.jpg"}], "usedIngredients": [{"id": 11352, "amount": 8.0, "unit": "inches", "unitLong": "inches", "unitShort": "inches", "aisle": "Produce", "name": "potatoes", "original": "4 smalls red potatoes (about 2 inches each)", "originalName": "smalls red potatoes (about each)", "meta": ["red"], "extendedName": "red potatoes", "image": "https://spoonacular.com/cdn/ingredients_100x100/potatoes-yukon-gold.png"}, {"id": 11955, "amount": 0.25, "unit": "cup", "unitLong": "cups", "unitShort": "cup", "aisle": "Canned and Jarred;Produce", "name": "sundried tomatoes", "original": "1/4 cup julienne-cut sundried tomatoes and herbs in oil, well dr", "originalName": "julienne-cut sundried tomatoes and herbs in oil, well dr", "meta": ["well", "in oil"], "image": "https://spoonacular.com/cdn/ingredients_100x100/sundried-tomatoes.jpg"}], "unusedIngredients": [], "likes": 1}, {"id": 641387, "title": "Delicious Creamy Lentils and Chestnuts Soup", "image": "https://spoonacular.com/recipeImages/641387-312x231.jpg", "imageType": "jpg", "usedIngredientCount": 2, "missedIngredientCount": 5, "missedIngredients": [{"id": 2004, "amount": 1.0, "unit": "", "unitLong": "", "unitShort": "", "aisle": "Spices and Seasonings", "name": "bay leaf", "original": "1 bay leaf", "originalName": "bay leaf", "meta": [], "image": "https://spoonacular.com/cdn/ingredients_100x100/bay-leaves.jpg"}, {"id": 12098, "amount": 0.25, "unit": "cup", "unitLong": "cups", "unitShort": "cup", "aisle": "Produce", "name": "chestnuts", "original": "1/4 cup of roasted chestnuts", "originalName": "roasted chestnuts", "meta": [], "image": "https://spoonacular.com/cdn/ingredients_100x100/chestnuts.jpg"}, {"id": 11215, "amount": 1.0, "unit": "clove", "unitLong": "clove", "unitShort": "clove", "aisle": "Produce", "name": "garlic", "original": "1 clove or garlic minced", "originalName": "or garlic minced", "meta": ["minced"], "image": "https://spoonacular.com/cdn/ingredients_100x100/garlic.png"}, {"id": 16069, "amount": 1.5, "unit": "cups", "unitLong": "cups", "unitShort": "cup", "aisle": "Pasta and Rice;Canned and Jarred;Produce", "name": "lentils", "original": "1 1/2 cups dry lentils", "originalName": "dry lentils", "meta": ["dry"], "extendedName": "dry lentils", "image": "https://spoonacular.com/cdn/ingredients_100x100/lentils-green.jpg"}, {"id": 11282, "amount": 1.0, "unit": "", "unitLong": "", "unitShort": "", "aisle": "Produce", "name": "onion", "original": "1 onion chopped", "originalName": "onion chopped", "meta": ["chopped"], "image": "https://spoonacular.com/cdn/ingredients_100x100/brown-onion.png"}], "usedIngredients": [{"id": 11352, "amount": 1.0, "unit": "", "unitLong": "", "unitShort": "", "aisle": "Produce", "name": "potato", "original": "1 potato", "originalName": "potato", "meta": [], "image": "https://spoonacular.com/cdn/ingredients_100x100/potatoes-yukon-gold.png"}, {"id": 10211529, "amount": 0.5, "unit": "cup", "unitLong": "cups", "unitShort": "cup", "aisle": "Produce", "name": "roma tomatoes", "original": "1/2 cup of sweet cherry tomatoes or Roma tomatoes chopped", "originalName": "sweet cherry tomatoes or Roma tomatoes chopped", "meta": ["sweet", "chopped"], "extendedName": "sweet roma tomatoes", "image": "https://spoonacular.com/cdn/ingredients_100x100/roma-tomatoes.png"}], "unusedIngredients": [], "likes": 1}]